FanghuMofaQuanshu/README.md
FanghuMofaQuanshu/__init__.py
FanghuMofaQuanshu/__main__.py
FanghuMofaQuanshu/file.epub
FanghuMofaQuanshu/index.html
FanghuMofaQuanshu/css/__init__.py
FanghuMofaQuanshu/css/annotations.css
FanghuMofaQuanshu/css/main.css
FanghuMofaQuanshu/css/normalize.css
FanghuMofaQuanshu/css/popup.css
FanghuMofaQuanshu/font/__init__.py
FanghuMofaQuanshu/font/fontello.eot
FanghuMofaQuanshu/font/fontello.svg
FanghuMofaQuanshu/font/fontello.ttf
FanghuMofaQuanshu/font/fontello.woff
FanghuMofaQuanshu/img/__init__.py
FanghuMofaQuanshu/img/annotator-glyph-sprite.png
FanghuMofaQuanshu/img/annotator-icon-sprite.png
FanghuMofaQuanshu/img/apple-touch-icon.png
FanghuMofaQuanshu/img/cancelfullscreen.png
FanghuMofaQuanshu/img/close.png
FanghuMofaQuanshu/img/fullscreen.png
FanghuMofaQuanshu/img/loader.gif
FanghuMofaQuanshu/img/menu-icon.png
FanghuMofaQuanshu/img/save.png
FanghuMofaQuanshu/img/saved.png
FanghuMofaQuanshu/img/settings-s.png
FanghuMofaQuanshu/img/settings.png
FanghuMofaQuanshu/img/star.png
FanghuMofaQuanshu/js/__init__.py
FanghuMofaQuanshu/js/epub.js
FanghuMofaQuanshu/js/epub.min.js
FanghuMofaQuanshu/js/epub.min.map
FanghuMofaQuanshu/js/hooks.min.js
FanghuMofaQuanshu/js/hooks.min.map
FanghuMofaQuanshu/js/reader.js
FanghuMofaQuanshu/js/reader.js.map
FanghuMofaQuanshu/js/reader.min.js
FanghuMofaQuanshu/js/reader.min.map
FanghuMofaQuanshu/js/hooks/__init__.py
FanghuMofaQuanshu/js/hooks/extensions/__init__.py
FanghuMofaQuanshu/js/hooks/extensions/highlight.js
FanghuMofaQuanshu/js/libs/__init__.py
FanghuMofaQuanshu/js/libs/jquery.min.js
FanghuMofaQuanshu/js/libs/localforage.min.js
FanghuMofaQuanshu/js/libs/screenfull.js
FanghuMofaQuanshu/js/libs/screenfull.min.js
FanghuMofaQuanshu/js/libs/zip.min.js
FanghuMofaQuanshu/js/plugins/__init__.py
FanghuMofaQuanshu/js/plugins/hypothesis.js
FanghuMofaQuanshu/js/plugins/search.js
fanghu_mofa_quanshu-2022.9.29.0.dist-info/METADATA
fanghu_mofa_quanshu-2022.9.29.0.dist-info/WHEEL
fanghu_mofa_quanshu-2022.9.29.0.dist-info/entry_points.txt
fanghu_mofa_quanshu-2022.9.29.0.dist-info/top_level.txt
fanghu_mofa_quanshu-2022.9.29.0.dist-info/RECORD
